{
  "manifestVersion": "3.2",
  "admin": {
    "address": "0xFF058F8390f7F08Cd282E030B8429e6566dc781A",
    "txHash": "0x8495a70765c4782e38195ba37dc8b85cca7c7c0ae7eba8efb7d0d203edc1a55d"
  },
  "proxies": [
    {
      "address": "0x0E4dB0A980cCf3Ac23F2c052C4591f84135cAd3C",
      "txHash": "0x736f0bfe964537150b5dbaa77fb3eff5da56e29fe958d23398eeba95829f584b",
      "kind": "transparent"
    },
    {
      "address": "0x84655a7BA3DE13B60F0C1Ac129BA49f844e839C8",
      "txHash": "0x6867d6487644148d13479cc96f90231743c404432944be02e3ef16ab7308affd",
      "kind": "transparent"
    },
    {
      "address": "0x6Ad46ae0B9423cA50031Ef07f69AE9670fc9dC73",
      "txHash": "0x4ff2c84f56f5a9afa5aba12179bde19b9d667a5db5568e088baf0ceed8931ac8",
      "kind": "transparent"
    }
  ],
  "impls": {
    "9694f12f04daa2040a0d746b7ce9148283a2080586748602ec431d19ea9bcb02": {
      "address": "0xdC68b23f51647a7C444175b50353Afc44927DB1D",
      "txHash": "0x7dd4d806cbef37690e5946997add03c3c44e9bfd90fd0ed960f840146fd32105",
      "layout": {
        "storage": [
          {
            "label": "_initialized",
            "offset": 0,
            "slot": "0",
            "type": "t_bool",
            "contract": "Initializable",
            "src": "@openzeppelin\\contracts-upgradeable\\proxy\\utils\\Initializable.sol:39"
          },
          {
            "label": "_initializing",
            "offset": 1,
            "slot": "0",
            "type": "t_bool",
            "contract": "Initializable",
            "src": "@openzeppelin\\contracts-upgradeable\\proxy\\utils\\Initializable.sol:44"
          },
          {
            "label": "__gap",
            "offset": 0,
            "slot": "1",
            "type": "t_array(t_uint256)50_storage",
            "contract": "ContextUpgradeable",
            "src": "@openzeppelin\\contracts-upgradeable\\utils\\ContextUpgradeable.sol:36"
          },
          {
            "label": "__gap",
            "offset": 0,
            "slot": "51",
            "type": "t_array(t_uint256)50_storage",
            "contract": "ERC165Upgradeable",
            "src": "@openzeppelin\\contracts-upgradeable\\utils\\introspection\\ERC165Upgradeable.sol:41"
          },
          {
            "label": "_name",
            "offset": 0,
            "slot": "101",
            "type": "t_string_storage",
            "contract": "ERC721Upgradeable",
            "src": "@openzeppelin\\contracts-upgradeable\\token\\ERC721\\ERC721Upgradeable.sol:25"
          },
          {
            "label": "_symbol",
            "offset": 0,
            "slot": "102",
            "type": "t_string_storage",
            "contract": "ERC721Upgradeable",
            "src": "@openzeppelin\\contracts-upgradeable\\token\\ERC721\\ERC721Upgradeable.sol:28"
          },
          {
            "label": "_owners",
            "offset": 0,
            "slot": "103",
            "type": "t_mapping(t_uint256,t_address)",
            "contract": "ERC721Upgradeable",
            "src": "@openzeppelin\\contracts-upgradeable\\token\\ERC721\\ERC721Upgradeable.sol:31"
          },
          {
            "label": "_balances",
            "offset": 0,
            "slot": "104",
            "type": "t_mapping(t_address,t_uint256)",
            "contract": "ERC721Upgradeable",
            "src": "@openzeppelin\\contracts-upgradeable\\token\\ERC721\\ERC721Upgradeable.sol:34"
          },
          {
            "label": "_tokenApprovals",
            "offset": 0,
            "slot": "105",
            "type": "t_mapping(t_uint256,t_address)",
            "contract": "ERC721Upgradeable",
            "src": "@openzeppelin\\contracts-upgradeable\\token\\ERC721\\ERC721Upgradeable.sol:37"
          },
          {
            "label": "_operatorApprovals",
            "offset": 0,
            "slot": "106",
            "type": "t_mapping(t_address,t_mapping(t_address,t_bool))",
            "contract": "ERC721Upgradeable",
            "src": "@openzeppelin\\contracts-upgradeable\\token\\ERC721\\ERC721Upgradeable.sol:40"
          },
          {
            "label": "__gap",
            "offset": 0,
            "slot": "107",
            "type": "t_array(t_uint256)44_storage",
            "contract": "ERC721Upgradeable",
            "src": "@openzeppelin\\contracts-upgradeable\\token\\ERC721\\ERC721Upgradeable.sol:458"
          },
          {
            "label": "_owner",
            "offset": 0,
            "slot": "151",
            "type": "t_address",
            "contract": "OwnableUpgradeable",
            "src": "@openzeppelin\\contracts-upgradeable\\access\\OwnableUpgradeable.sol:22"
          },
          {
            "label": "__gap",
            "offset": 0,
            "slot": "152",
            "type": "t_array(t_uint256)49_storage",
            "contract": "OwnableUpgradeable",
            "src": "@openzeppelin\\contracts-upgradeable\\access\\OwnableUpgradeable.sol:87"
          },
          {
            "label": "__gap",
            "offset": 0,
            "slot": "201",
            "type": "t_array(t_uint256)50_storage",
            "contract": "ERC721HolderUpgradeable",
            "src": "@openzeppelin\\contracts-upgradeable\\token\\ERC721\\utils\\ERC721HolderUpgradeable.sol:40"
          },
          {
            "label": "_status",
            "offset": 0,
            "slot": "251",
            "type": "t_uint256",
            "contract": "ReentrancyGuardUpgradeable",
            "src": "@openzeppelin\\contracts-upgradeable\\security\\ReentrancyGuardUpgradeable.sol:38"
          },
          {
            "label": "__gap",
            "offset": 0,
            "slot": "252",
            "type": "t_array(t_uint256)49_storage",
            "contract": "ReentrancyGuardUpgradeable",
            "src": "@openzeppelin\\contracts-upgradeable\\security\\ReentrancyGuardUpgradeable.sol:74"
          },
          {
            "label": "params",
            "offset": 0,
            "slot": "301",
            "type": "t_contract(ILotteryParams)2941",
            "contract": "NFTLotteryPool",
            "src": "contracts\\NFTLotteryPool.sol:38"
          },
          {
            "label": "distributor",
            "offset": 0,
            "slot": "302",
            "type": "t_contract(IDistributor)2957",
            "contract": "NFTLotteryPool",
            "src": "contracts\\NFTLotteryPool.sol:39"
          },
          {
            "label": "link",
            "offset": 0,
            "slot": "303",
            "type": "t_contract(IERC20Upgradeable)334",
            "contract": "NFTLotteryPool",
            "src": "contracts\\NFTLotteryPool.sol:40"
          },
          {
            "label": "prizeAddress",
            "offset": 0,
            "slot": "304",
            "type": "t_address",
            "contract": "NFTLotteryPool",
            "src": "contracts\\NFTLotteryPool.sol:43"
          },
          {
            "label": "prizeId",
            "offset": 0,
            "slot": "305",
            "type": "t_uint256",
            "contract": "NFTLotteryPool",
            "src": "contracts\\NFTLotteryPool.sol:44"
          },
          {
            "label": "startDate",
            "offset": 0,
            "slot": "306",
            "type": "t_uint64",
            "contract": "NFTLotteryPool",
            "src": "contracts\\NFTLotteryPool.sol:45"
          },
          {
            "label": "endDate",
            "offset": 8,
            "slot": "306",
            "type": "t_uint64",
            "contract": "NFTLotteryPool",
            "src": "contracts\\NFTLotteryPool.sol:46"
          },
          {
            "label": "minTicketsToSell",
            "offset": 16,
            "slot": "306",
            "type": "t_uint32",
            "contract": "NFTLotteryPool",
            "src": "contracts\\NFTLotteryPool.sol:47"
          },
          {
            "label": "maxTickets",
            "offset": 20,
            "slot": "306",
            "type": "t_uint32",
            "contract": "NFTLotteryPool",
            "src": "contracts\\NFTLotteryPool.sol:48"
          },
          {
            "label": "maxTicketsPerAddress",
            "offset": 24,
            "slot": "306",
            "type": "t_uint32",
            "contract": "NFTLotteryPool",
            "src": "contracts\\NFTLotteryPool.sol:49"
          },
          {
            "label": "ticketPrice",
            "offset": 0,
            "slot": "307",
            "type": "t_uint256",
            "contract": "NFTLotteryPool",
            "src": "contracts\\NFTLotteryPool.sol:50"
          },
          {
            "label": "hasCalledVRF",
            "offset": 0,
            "slot": "308",
            "type": "t_bool",
            "contract": "NFTLotteryPool",
            "src": "contracts\\NFTLotteryPool.sol:53"
          },
          {
            "label": "isRefundOpen",
            "offset": 1,
            "slot": "308",
            "type": "t_bool",
            "contract": "NFTLotteryPool",
            "src": "contracts\\NFTLotteryPool.sol:56"
          },
          {
            "label": "tokenCounter",
            "offset": 0,
            "slot": "309",
            "type": "t_uint256",
            "contract": "NFTLotteryPool",
            "src": "contracts\\NFTLotteryPool.sol:58"
          }
        ],
        "types": {
          "t_address": {
            "label": "address",
            "numberOfBytes": "20"
          },
          "t_array(t_uint256)44_storage": {
            "label": "uint256[44]",
            "numberOfBytes": "1408"
          },
          "t_array(t_uint256)49_storage": {
            "label": "uint256[49]",
            "numberOfBytes": "1568"
          },
          "t_array(t_uint256)50_storage": {
            "label": "uint256[50]",
            "numberOfBytes": "1600"
          },
          "t_bool": {
            "label": "bool",
            "numberOfBytes": "1"
          },
          "t_contract(IDistributor)2957": {
            "label": "contract IDistributor",
            "numberOfBytes": "20"
          },
          "t_contract(IERC20Upgradeable)334": {
            "label": "contract IERC20Upgradeable",
            "numberOfBytes": "20"
          },
          "t_contract(ILotteryParams)2941": {
            "label": "contract ILotteryParams",
            "numberOfBytes": "20"
          },
          "t_mapping(t_address,t_bool)": {
            "label": "mapping(address => bool)",
            "numberOfBytes": "32"
          },
          "t_mapping(t_address,t_mapping(t_address,t_bool))": {
            "label": "mapping(address => mapping(address => bool))",
            "numberOfBytes": "32"
          },
          "t_mapping(t_address,t_uint256)": {
            "label": "mapping(address => uint256)",
            "numberOfBytes": "32"
          },
          "t_mapping(t_uint256,t_address)": {
            "label": "mapping(uint256 => address)",
            "numberOfBytes": "32"
          },
          "t_string_storage": {
            "label": "string",
            "numberOfBytes": "32"
          },
          "t_uint256": {
            "label": "uint256",
            "numberOfBytes": "32"
          },
          "t_uint32": {
            "label": "uint32",
            "numberOfBytes": "4"
          },
          "t_uint64": {
            "label": "uint64",
            "numberOfBytes": "8"
          }
        }
      }
    },
    "c4864661359f741c69d3e9045949e4265160e124c8b4aa4fcac4e50355deb9aa": {
      "address": "0x1d806208b409aa9242C1D532eF862Cc813ae32F3",
      "txHash": "0xb15ea16976c491f2aa88db0852b6b84bff1426b8d1dd1c70d1448ccbb88e3bb5",
      "layout": {
        "storage": [
          {
            "label": "_initialized",
            "offset": 0,
            "slot": "0",
            "type": "t_bool",
            "contract": "Initializable",
            "src": "@openzeppelin\\contracts-upgradeable\\proxy\\utils\\Initializable.sol:39"
          },
          {
            "label": "_initializing",
            "offset": 1,
            "slot": "0",
            "type": "t_bool",
            "contract": "Initializable",
            "src": "@openzeppelin\\contracts-upgradeable\\proxy\\utils\\Initializable.sol:44"
          },
          {
            "label": "__gap",
            "offset": 0,
            "slot": "1",
            "type": "t_array(t_uint256)50_storage",
            "contract": "ContextUpgradeable",
            "src": "@openzeppelin\\contracts-upgradeable\\utils\\ContextUpgradeable.sol:36"
          },
          {
            "label": "__gap",
            "offset": 0,
            "slot": "51",
            "type": "t_array(t_uint256)50_storage",
            "contract": "ERC165Upgradeable",
            "src": "@openzeppelin\\contracts-upgradeable\\utils\\introspection\\ERC165Upgradeable.sol:41"
          },
          {
            "label": "_name",
            "offset": 0,
            "slot": "101",
            "type": "t_string_storage",
            "contract": "ERC721Upgradeable",
            "src": "@openzeppelin\\contracts-upgradeable\\token\\ERC721\\ERC721Upgradeable.sol:25"
          },
          {
            "label": "_symbol",
            "offset": 0,
            "slot": "102",
            "type": "t_string_storage",
            "contract": "ERC721Upgradeable",
            "src": "@openzeppelin\\contracts-upgradeable\\token\\ERC721\\ERC721Upgradeable.sol:28"
          },
          {
            "label": "_owners",
            "offset": 0,
            "slot": "103",
            "type": "t_mapping(t_uint256,t_address)",
            "contract": "ERC721Upgradeable",
            "src": "@openzeppelin\\contracts-upgradeable\\token\\ERC721\\ERC721Upgradeable.sol:31"
          },
          {
            "label": "_balances",
            "offset": 0,
            "slot": "104",
            "type": "t_mapping(t_address,t_uint256)",
            "contract": "ERC721Upgradeable",
            "src": "@openzeppelin\\contracts-upgradeable\\token\\ERC721\\ERC721Upgradeable.sol:34"
          },
          {
            "label": "_tokenApprovals",
            "offset": 0,
            "slot": "105",
            "type": "t_mapping(t_uint256,t_address)",
            "contract": "ERC721Upgradeable",
            "src": "@openzeppelin\\contracts-upgradeable\\token\\ERC721\\ERC721Upgradeable.sol:37"
          },
          {
            "label": "_operatorApprovals",
            "offset": 0,
            "slot": "106",
            "type": "t_mapping(t_address,t_mapping(t_address,t_bool))",
            "contract": "ERC721Upgradeable",
            "src": "@openzeppelin\\contracts-upgradeable\\token\\ERC721\\ERC721Upgradeable.sol:40"
          },
          {
            "label": "__gap",
            "offset": 0,
            "slot": "107",
            "type": "t_array(t_uint256)44_storage",
            "contract": "ERC721Upgradeable",
            "src": "@openzeppelin\\contracts-upgradeable\\token\\ERC721\\ERC721Upgradeable.sol:458"
          },
          {
            "label": "_owner",
            "offset": 0,
            "slot": "151",
            "type": "t_address",
            "contract": "OwnableUpgradeable",
            "src": "@openzeppelin\\contracts-upgradeable\\access\\OwnableUpgradeable.sol:22"
          },
          {
            "label": "__gap",
            "offset": 0,
            "slot": "152",
            "type": "t_array(t_uint256)49_storage",
            "contract": "OwnableUpgradeable",
            "src": "@openzeppelin\\contracts-upgradeable\\access\\OwnableUpgradeable.sol:87"
          },
          {
            "label": "__gap",
            "offset": 0,
            "slot": "201",
            "type": "t_array(t_uint256)50_storage",
            "contract": "ERC721HolderUpgradeable",
            "src": "@openzeppelin\\contracts-upgradeable\\token\\ERC721\\utils\\ERC721HolderUpgradeable.sol:40"
          },
          {
            "label": "_status",
            "offset": 0,
            "slot": "251",
            "type": "t_uint256",
            "contract": "ReentrancyGuardUpgradeable",
            "src": "@openzeppelin\\contracts-upgradeable\\security\\ReentrancyGuardUpgradeable.sol:38"
          },
          {
            "label": "__gap",
            "offset": 0,
            "slot": "252",
            "type": "t_array(t_uint256)49_storage",
            "contract": "ReentrancyGuardUpgradeable",
            "src": "@openzeppelin\\contracts-upgradeable\\security\\ReentrancyGuardUpgradeable.sol:74"
          },
          {
            "label": "params",
            "offset": 0,
            "slot": "301",
            "type": "t_contract(ILotteryParams)2941",
            "contract": "NFTLotteryPool",
            "src": "contracts\\NFTLotteryPool.sol:38"
          },
          {
            "label": "distributor",
            "offset": 0,
            "slot": "302",
            "type": "t_contract(IDistributor)2957",
            "contract": "NFTLotteryPool",
            "src": "contracts\\NFTLotteryPool.sol:39"
          },
          {
            "label": "link",
            "offset": 0,
            "slot": "303",
            "type": "t_contract(IERC20Upgradeable)334",
            "contract": "NFTLotteryPool",
            "src": "contracts\\NFTLotteryPool.sol:40"
          },
          {
            "label": "prizeAddress",
            "offset": 0,
            "slot": "304",
            "type": "t_address",
            "contract": "NFTLotteryPool",
            "src": "contracts\\NFTLotteryPool.sol:43"
          },
          {
            "label": "prizeId",
            "offset": 0,
            "slot": "305",
            "type": "t_uint256",
            "contract": "NFTLotteryPool",
            "src": "contracts\\NFTLotteryPool.sol:44"
          },
          {
            "label": "startDate",
            "offset": 0,
            "slot": "306",
            "type": "t_uint64",
            "contract": "NFTLotteryPool",
            "src": "contracts\\NFTLotteryPool.sol:45"
          },
          {
            "label": "endDate",
            "offset": 8,
            "slot": "306",
            "type": "t_uint64",
            "contract": "NFTLotteryPool",
            "src": "contracts\\NFTLotteryPool.sol:46"
          },
          {
            "label": "minTicketsToSell",
            "offset": 16,
            "slot": "306",
            "type": "t_uint32",
            "contract": "NFTLotteryPool",
            "src": "contracts\\NFTLotteryPool.sol:47"
          },
          {
            "label": "maxTickets",
            "offset": 20,
            "slot": "306",
            "type": "t_uint32",
            "contract": "NFTLotteryPool",
            "src": "contracts\\NFTLotteryPool.sol:48"
          },
          {
            "label": "maxTicketsPerAddress",
            "offset": 24,
            "slot": "306",
            "type": "t_uint32",
            "contract": "NFTLotteryPool",
            "src": "contracts\\NFTLotteryPool.sol:49"
          },
          {
            "label": "ticketPrice",
            "offset": 0,
            "slot": "307",
            "type": "t_uint256",
            "contract": "NFTLotteryPool",
            "src": "contracts\\NFTLotteryPool.sol:50"
          },
          {
            "label": "hasCalledVRF",
            "offset": 0,
            "slot": "308",
            "type": "t_bool",
            "contract": "NFTLotteryPool",
            "src": "contracts\\NFTLotteryPool.sol:53"
          },
          {
            "label": "isRefundOpen",
            "offset": 1,
            "slot": "308",
            "type": "t_bool",
            "contract": "NFTLotteryPool",
            "src": "contracts\\NFTLotteryPool.sol:56"
          },
          {
            "label": "tokenCounter",
            "offset": 0,
            "slot": "309",
            "type": "t_uint256",
            "contract": "NFTLotteryPool",
            "src": "contracts\\NFTLotteryPool.sol:58"
          }
        ],
        "types": {
          "t_address": {
            "label": "address",
            "numberOfBytes": "20"
          },
          "t_array(t_uint256)44_storage": {
            "label": "uint256[44]",
            "numberOfBytes": "1408"
          },
          "t_array(t_uint256)49_storage": {
            "label": "uint256[49]",
            "numberOfBytes": "1568"
          },
          "t_array(t_uint256)50_storage": {
            "label": "uint256[50]",
            "numberOfBytes": "1600"
          },
          "t_bool": {
            "label": "bool",
            "numberOfBytes": "1"
          },
          "t_contract(IDistributor)2957": {
            "label": "contract IDistributor",
            "numberOfBytes": "20"
          },
          "t_contract(IERC20Upgradeable)334": {
            "label": "contract IERC20Upgradeable",
            "numberOfBytes": "20"
          },
          "t_contract(ILotteryParams)2941": {
            "label": "contract ILotteryParams",
            "numberOfBytes": "20"
          },
          "t_mapping(t_address,t_bool)": {
            "label": "mapping(address => bool)",
            "numberOfBytes": "32"
          },
          "t_mapping(t_address,t_mapping(t_address,t_bool))": {
            "label": "mapping(address => mapping(address => bool))",
            "numberOfBytes": "32"
          },
          "t_mapping(t_address,t_uint256)": {
            "label": "mapping(address => uint256)",
            "numberOfBytes": "32"
          },
          "t_mapping(t_uint256,t_address)": {
            "label": "mapping(uint256 => address)",
            "numberOfBytes": "32"
          },
          "t_string_storage": {
            "label": "string",
            "numberOfBytes": "32"
          },
          "t_uint256": {
            "label": "uint256",
            "numberOfBytes": "32"
          },
          "t_uint32": {
            "label": "uint32",
            "numberOfBytes": "4"
          },
          "t_uint64": {
            "label": "uint64",
            "numberOfBytes": "8"
          }
        }
      }
    },
    "d80cefb209d37e828d85c3c53a58cff31abc77c1941730e0ab471ccdf9a42330": {
      "address": "0x28CeA3831412c352743fAE90739E0bC47EE86e87",
      "txHash": "0x5783ed45765bf08e713f0fefd9e63d6158b46c16e1422ca9dcdd9930114ed0e5",
      "layout": {
        "storage": [
          {
            "label": "_initialized",
            "offset": 0,
            "slot": "0",
            "type": "t_bool",
            "contract": "Initializable",
            "src": "@openzeppelin\\contracts-upgradeable\\proxy\\utils\\Initializable.sol:39"
          },
          {
            "label": "_initializing",
            "offset": 1,
            "slot": "0",
            "type": "t_bool",
            "contract": "Initializable",
            "src": "@openzeppelin\\contracts-upgradeable\\proxy\\utils\\Initializable.sol:44"
          },
          {
            "label": "_status",
            "offset": 0,
            "slot": "1",
            "type": "t_uint256",
            "contract": "ReentrancyGuardUpgradeable",
            "src": "@openzeppelin\\contracts-upgradeable\\security\\ReentrancyGuardUpgradeable.sol:38"
          },
          {
            "label": "__gap",
            "offset": 0,
            "slot": "2",
            "type": "t_array(t_uint256)49_storage",
            "contract": "ReentrancyGuardUpgradeable",
            "src": "@openzeppelin\\contracts-upgradeable\\security\\ReentrancyGuardUpgradeable.sol:74"
          },
          {
            "label": "__gap",
            "offset": 0,
            "slot": "51",
            "type": "t_array(t_uint256)50_storage",
            "contract": "ContextUpgradeable",
            "src": "@openzeppelin\\contracts-upgradeable\\utils\\ContextUpgradeable.sol:36"
          },
          {
            "label": "_owner",
            "offset": 0,
            "slot": "101",
            "type": "t_address",
            "contract": "OwnableUpgradeable",
            "src": "@openzeppelin\\contracts-upgradeable\\access\\OwnableUpgradeable.sol:22"
          },
          {
            "label": "__gap",
            "offset": 0,
            "slot": "102",
            "type": "t_array(t_uint256)49_storage",
            "contract": "OwnableUpgradeable",
            "src": "@openzeppelin\\contracts-upgradeable\\access\\OwnableUpgradeable.sol:87"
          },
          {
            "label": "__gap",
            "offset": 0,
            "slot": "151",
            "type": "t_array(t_uint256)50_storage",
            "contract": "ERC165Upgradeable",
            "src": "@openzeppelin\\contracts-upgradeable\\utils\\introspection\\ERC165Upgradeable.sol:41"
          },
          {
            "label": "_name",
            "offset": 0,
            "slot": "201",
            "type": "t_string_storage",
            "contract": "ERC721Upgradeable",
            "src": "@openzeppelin\\contracts-upgradeable\\token\\ERC721\\ERC721Upgradeable.sol:25"
          },
          {
            "label": "_symbol",
            "offset": 0,
            "slot": "202",
            "type": "t_string_storage",
            "contract": "ERC721Upgradeable",
            "src": "@openzeppelin\\contracts-upgradeable\\token\\ERC721\\ERC721Upgradeable.sol:28"
          },
          {
            "label": "_owners",
            "offset": 0,
            "slot": "203",
            "type": "t_mapping(t_uint256,t_address)",
            "contract": "ERC721Upgradeable",
            "src": "@openzeppelin\\contracts-upgradeable\\token\\ERC721\\ERC721Upgradeable.sol:31"
          },
          {
            "label": "_balances",
            "offset": 0,
            "slot": "204",
            "type": "t_mapping(t_address,t_uint256)",
            "contract": "ERC721Upgradeable",
            "src": "@openzeppelin\\contracts-upgradeable\\token\\ERC721\\ERC721Upgradeable.sol:34"
          },
          {
            "label": "_tokenApprovals",
            "offset": 0,
            "slot": "205",
            "type": "t_mapping(t_uint256,t_address)",
            "contract": "ERC721Upgradeable",
            "src": "@openzeppelin\\contracts-upgradeable\\token\\ERC721\\ERC721Upgradeable.sol:37"
          },
          {
            "label": "_operatorApprovals",
            "offset": 0,
            "slot": "206",
            "type": "t_mapping(t_address,t_mapping(t_address,t_bool))",
            "contract": "ERC721Upgradeable",
            "src": "@openzeppelin\\contracts-upgradeable\\token\\ERC721\\ERC721Upgradeable.sol:40"
          },
          {
            "label": "__gap",
            "offset": 0,
            "slot": "207",
            "type": "t_array(t_uint256)44_storage",
            "contract": "ERC721Upgradeable",
            "src": "@openzeppelin\\contracts-upgradeable\\token\\ERC721\\ERC721Upgradeable.sol:458"
          },
          {
            "label": "_ownedTokens",
            "offset": 0,
            "slot": "251",
            "type": "t_mapping(t_address,t_mapping(t_uint256,t_uint256))",
            "contract": "ERC721EnumerableUpgradeable",
            "src": "@openzeppelin\\contracts-upgradeable\\token\\ERC721\\extensions\\ERC721EnumerableUpgradeable.sol:22"
          },
          {
            "label": "_ownedTokensIndex",
            "offset": 0,
            "slot": "252",
            "type": "t_mapping(t_uint256,t_uint256)",
            "contract": "ERC721EnumerableUpgradeable",
            "src": "@openzeppelin\\contracts-upgradeable\\token\\ERC721\\extensions\\ERC721EnumerableUpgradeable.sol:25"
          },
          {
            "label": "_allTokens",
            "offset": 0,
            "slot": "253",
            "type": "t_array(t_uint256)dyn_storage",
            "contract": "ERC721EnumerableUpgradeable",
            "src": "@openzeppelin\\contracts-upgradeable\\token\\ERC721\\extensions\\ERC721EnumerableUpgradeable.sol:28"
          },
          {
            "label": "_allTokensIndex",
            "offset": 0,
            "slot": "254",
            "type": "t_mapping(t_uint256,t_uint256)",
            "contract": "ERC721EnumerableUpgradeable",
            "src": "@openzeppelin\\contracts-upgradeable\\token\\ERC721\\extensions\\ERC721EnumerableUpgradeable.sol:31"
          },
          {
            "label": "__gap",
            "offset": 0,
            "slot": "255",
            "type": "t_array(t_uint256)46_storage",
            "contract": "ERC721EnumerableUpgradeable",
            "src": "@openzeppelin\\contracts-upgradeable\\token\\ERC721\\extensions\\ERC721EnumerableUpgradeable.sol:175"
          },
          {
            "label": "_defaultRoyaltyInfo",
            "offset": 0,
            "slot": "301",
            "type": "t_struct(RoyaltyInfo)2094_storage",
            "contract": "ERC2981Upgradeable",
            "src": "@openzeppelin\\contracts-upgradeable\\token\\common\\ERC2981Upgradeable.sol:36"
          },
          {
            "label": "_tokenRoyaltyInfo",
            "offset": 0,
            "slot": "302",
            "type": "t_mapping(t_uint256,t_struct(RoyaltyInfo)2094_storage)",
            "contract": "ERC2981Upgradeable",
            "src": "@openzeppelin\\contracts-upgradeable\\token\\common\\ERC2981Upgradeable.sol:37"
          },
          {
            "label": "__gap",
            "offset": 0,
            "slot": "303",
            "type": "t_array(t_uint256)48_storage",
            "contract": "ERC2981Upgradeable",
            "src": "@openzeppelin\\contracts-upgradeable\\token\\common\\ERC2981Upgradeable.sol:130"
          },
          {
            "label": "defaultRoyaltyInfo",
            "offset": 0,
            "slot": "351",
            "type": "t_struct(RoyaltyInfo)2094_storage",
            "contract": "TokenMintERC721",
            "src": "contracts\\TokenMintERC721.sol:16"
          },
          {
            "label": "_tokenCounter",
            "offset": 0,
            "slot": "352",
            "type": "t_uint256",
            "contract": "TokenMintERC721",
            "src": "contracts\\TokenMintERC721.sol:27"
          },
          {
            "label": "treasury",
            "offset": 0,
            "slot": "353",
            "type": "t_address",
            "contract": "TokenMintERC721",
            "src": "contracts\\TokenMintERC721.sol:32"
          },
          {
            "label": "_admins",
            "offset": 0,
            "slot": "354",
            "type": "t_mapping(t_address,t_bool)",
            "contract": "TokenMintERC721",
            "src": "contracts\\TokenMintERC721.sol:37"
          },
          {
            "label": "uris",
            "offset": 0,
            "slot": "355",
            "type": "t_mapping(t_uint256,t_string_storage)",
            "contract": "TokenMintERC721",
            "src": "contracts\\TokenMintERC721.sol:42"
          }
        ],
        "types": {
          "t_address": {
            "label": "address",
            "numberOfBytes": "20"
          },
          "t_array(t_uint256)44_storage": {
            "label": "uint256[44]",
            "numberOfBytes": "1408"
          },
          "t_array(t_uint256)46_storage": {
            "label": "uint256[46]",
            "numberOfBytes": "1472"
          },
          "t_array(t_uint256)48_storage": {
            "label": "uint256[48]",
            "numberOfBytes": "1536"
          },
          "t_array(t_uint256)49_storage": {
            "label": "uint256[49]",
            "numberOfBytes": "1568"
          },
          "t_array(t_uint256)50_storage": {
            "label": "uint256[50]",
            "numberOfBytes": "1600"
          },
          "t_array(t_uint256)dyn_storage": {
            "label": "uint256[]",
            "numberOfBytes": "32"
          },
          "t_bool": {
            "label": "bool",
            "numberOfBytes": "1"
          },
          "t_mapping(t_address,t_bool)": {
            "label": "mapping(address => bool)",
            "numberOfBytes": "32"
          },
          "t_mapping(t_address,t_mapping(t_address,t_bool))": {
            "label": "mapping(address => mapping(address => bool))",
            "numberOfBytes": "32"
          },
          "t_mapping(t_address,t_mapping(t_uint256,t_uint256))": {
            "label": "mapping(address => mapping(uint256 => uint256))",
            "numberOfBytes": "32"
          },
          "t_mapping(t_address,t_uint256)": {
            "label": "mapping(address => uint256)",
            "numberOfBytes": "32"
          },
          "t_mapping(t_uint256,t_address)": {
            "label": "mapping(uint256 => address)",
            "numberOfBytes": "32"
          },
          "t_mapping(t_uint256,t_string_storage)": {
            "label": "mapping(uint256 => string)",
            "numberOfBytes": "32"
          },
          "t_mapping(t_uint256,t_struct(RoyaltyInfo)2094_storage)": {
            "label": "mapping(uint256 => struct ERC2981Upgradeable.RoyaltyInfo)",
            "numberOfBytes": "32"
          },
          "t_mapping(t_uint256,t_uint256)": {
            "label": "mapping(uint256 => uint256)",
            "numberOfBytes": "32"
          },
          "t_string_storage": {
            "label": "string",
            "numberOfBytes": "32"
          },
          "t_struct(RoyaltyInfo)2094_storage": {
            "label": "struct ERC2981Upgradeable.RoyaltyInfo",
            "members": [
              {
                "label": "receiver",
                "type": "t_address",
                "offset": 0,
                "slot": "0"
              },
              {
                "label": "royaltyFraction",
                "type": "t_uint96",
                "offset": 20,
                "slot": "0"
              }
            ],
            "numberOfBytes": "32"
          },
          "t_uint256": {
            "label": "uint256",
            "numberOfBytes": "32"
          },
          "t_uint96": {
            "label": "uint96",
            "numberOfBytes": "12"
          }
        }
      }
    }
  }
}
